{
    "plugins": [
        "CVFParser",
        "GitHubLinkParser",
        "DefaultKeywordsParser",
        "MarkdownTableMaker",
        "DownloadInformationCollector",
        "ResultSaverByDefaultKeywordParser",
        "TranslatorWithDefaultKeywordsParser",
        "ResultSaverByDefaultKeywordParser",
        "DownloadedPaperIndexGenerator"
    ],
    "configs": {
        "CVFParser": {
            "year": 2023,
            "conference": "CVPR",
            "output_directory": "outputs/CVPR/2023",
            "num_requested": null
        },
        "ResultSaverByDefaultKeywordParser": {
            "output_directory": "outputs/CVPR/2023",
            "markdown_directory": "../../Notebook/journal/CVPR/2023"
        },
        "DefaultKeywordsParser": {
            "keywords": {
                "detect": ["detect", "detection"],
                "segment": ["segment", "segmentation"]
            },
            "ignorance": {
                "detect": [
                    " disease ", " cancer ", " medical ", " polyp ", " lesion ",
                    " mri ", " tumor ", " lidar ", " remote sens", " audio ", " video ",
                    " tracking ", " video ", " 3d ", " point cloud", " covid-19 ",
                    " vehicle", " Bird's Eye View ", " BEV ", " surgery ", " Cardiac ",
                    " deepfake ", " out-of-distribution ", " toxicity ", " speech ",
                    " fraud ", " traffic ", " salient object ", " self-driving ",
                    " emotion ", " anomaly ", " Meningeal ", " Lymphatic ", " Vessel ",
                    " music ", " clinical ", " economist", " Jailbreak ", " Vessel ",
                    " Clinical ", " Spatiotemporal ", "Crack Segmentation"
                ],
                "segment": [
                    " disease ", " cancer ", " medical ", " polyp ", " lesion ",
                    " mri ", " tumor ", " lidar ", " remote sens", " audio ", " video ",
                    " tracking ", " video ", " 3d ", " point cloud", " covid-19 ",
                    " vehicle", " Bird's Eye View ", " BEV ", " surgery ", " Cardiac ",
                    " deepfake ", " out-of-distribution ", " toxicity ", " speech ",
                    " fraud ", " traffic ", " salient object ", " self-driving ",
                    " emotion ", " anomaly ", " Meningeal ", " Lymphatic ", " Vessel ",
                    " music ", " clinical ", " economist", " Jailbreak ", " Vessel ",
                    " Clinical ", " Spatiotemporal ", "Crack Segmentation"
                ]
            }
        }
    }
}